pixel_panel/__init__.py
pixel_panel/color.py
pixel_panel/font.py
pixel_panel/pixel_panel.py
pixel_panel/text.py
pixel_panel-0.1.2.dist-info/top_level.txt
pixel_panel-0.1.2.dist-info/METADATA
pixel_panel-0.1.2.dist-info/DESCRIPTION.rst
pixel_panel-0.1.2.dist-info/metadata.json
pixel_panel-0.1.2.dist-info/WHEEL
pixel_panel-0.1.2.dist-info/RECORD
